LICENSE
README.md
setup.py
transpose/__init__.py
transpose/chart.py
transpose/sql/__init__.py
transpose/sql/general.py
transpose/sql/ohlc.py
transpose/sql/token.py
transpose/utils/__init__.py
transpose/utils/address.py
transpose/utils/exceptions.py
transpose/utils/request.py
transpose/utils/time.py
transpose_defi_sdk.egg-info/PKG-INFO
transpose_defi_sdk.egg-info/SOURCES.txt
transpose_defi_sdk.egg-info/dependency_links.txt
transpose_defi_sdk.egg-info/requires.txt
transpose_defi_sdk.egg-info/top_level.txt