Metadata-Version: 2.1
Name: transpose-defi-sdk
Version: 1.0.1
Summary: The Transpose DeFi SDK is a simple Python package for performing multi-chain DeFi analysis using the real-time Transpose SQL API.
Home-page: https://github.com/TransposeData/transpose-defi-sdk
Author: Alex Langshur (alangshur)
Author-email: alex@transpose.io
License: MIT
Keywords: web3,defi,ethereum,transpose,prices,ohlc,data,analysis,blockchain,polygon
Classifier: Development Status :: 3 - Alpha
Classifier: Intended Audience :: Developers
Classifier: Intended Audience :: Information Technology
Classifier: License :: OSI Approved :: MIT License
Classifier: Natural Language :: English
Classifier: Topic :: Database
Classifier: Topic :: Utilities
License-File: LICENSE
